{"type":"PR","pr":{"number":24,"head":"2d3a6fc7012eeff1c9baf7ab93123d6d64a82e47"},"user":"Stanzilla","status":"draft","branch":"cms/events/game-jam-2","collection":"events","commitMessage":"Create events “game-jam-2”","title":"Game Jam 2","description":"No Description!","objects":{"entry":{"path":"src/events/game-jam-2.md","sha":"802527b6f90333a408789afbee848a8db2ff730c"},"files":[{"path":"src/img/e2360541-9cb4-418f-b574-8d654b0ef961.png","sha":"b38707ba9e6cc8f7e39b389d5cb9833598009281"}]},"timeStamp":"2020-01-07T22:27:33.023Z","version":"1"}